{"version":3,"kind":"Article","sha256":"8745536ce265887464857f29ff77c51584522cefee403be381fe64251f25d0e4","slug":"filter-doc","location":"/../modules/filter/filter_doc.md","dependencies":[],"frontmatter":{"title":"FILTER - Filter","content_includes_title":false,"github":"https://github.com/PandABlocks/PandABlocks-FPGA","numbering":{"title":{"offset":2}},"source_url":"https://github.com/PandABlocks/PandABlocks-FPGA/blob/main/modules/filter/filter_doc.md","edit_url":"https://github.com/PandABlocks/PandABlocks-FPGA/edit/main/modules/filter/filter_doc.md","thumbnail":"/PandABlocks-FPGA/docs/build/91ace76e3fbeafee-f18fd401c6acd1b8f0ee1c179351a481.svg","exports":[{"format":"md","filename":"filter_doc.md","url":"/PandABlocks-FPGA/docs/build/filter_doc-981be9e331a20fe5e731bfe8a183578e.md"}]},"mdast":{"type":"root","children":[{"type":"block","children":[{"type":"paragraph","position":{"start":{"line":3,"column":1},"end":{"line":5,"column":1}},"children":[{"type":"text","value":"The filter block has two different modes of operation: Difference and Average.\nThey both work by latching the values on the input and performing an operation\ncomparing to the current value.","position":{"start":{"line":3,"column":1},"end":{"line":3,"column":1}},"key":"Bp2jTOWCyS"}],"key":"HKm3McRPZj"},{"type":"heading","depth":2,"position":{"start":{"line":7,"column":1},"end":{"line":7,"column":1}},"children":[{"type":"text","value":"Fields","position":{"start":{"line":7,"column":1},"end":{"line":7,"column":1}},"key":"YUuJUgNV4s"}],"identifier":"fields","label":"Fields","html_id":"fields","implicit":true,"key":"sURwNLHiWF"},{"type":"table","children":[{"type":"tableRow","children":[{"type":"tableCell","children":[{"type":"text","value":"Name","key":"VqpcpcMmAG"}],"header":true,"key":"qzTHAE8tXZ"},{"type":"tableCell","children":[{"type":"text","value":"Type","key":"zjs9z1SwIC"}],"header":true,"key":"vlc95wkmvC"},{"type":"tableCell","children":[{"type":"text","value":"Description","key":"XKC0QYdGUK"}],"header":true,"key":"hvlofz1WsE"}],"key":"glXWduLlgB"},{"type":"tableRow","children":[{"type":"tableCell","children":[{"type":"text","value":"ENABLE","key":"eISXDpdyZU"}],"key":"ZZd7D63uND"},{"type":"tableCell","children":[{"type":"text","value":"bit_mux","key":"TCISwuOJWk"}],"key":"LUoWbcjBH7"},{"type":"tableCell","children":[{"type":"text","value":"Enable event","key":"N8Ufr382Xy"}],"key":"AIlCYYG6Wr"}],"key":"XOch3R6uPy"},{"type":"tableRow","children":[{"type":"tableCell","children":[{"type":"text","value":"TRIG","key":"C0PLpy5XbW"}],"key":"E60q80Izow"},{"type":"tableCell","children":[{"type":"text","value":"bit_mux","key":"p7zd0hFv4n"}],"key":"A0vHHAddDk"},{"type":"tableCell","children":[{"type":"text","value":"Trigger event","key":"sPUiVryW7J"}],"key":"NeolqOQFOR"}],"key":"JBs5X4lJKC"},{"type":"tableRow","children":[{"type":"tableCell","children":[{"type":"text","value":"INP","key":"NM1iuhvl6d"}],"key":"wdMlhcpszA"},{"type":"tableCell","children":[{"type":"text","value":"pos_mux","key":"TivNUca8hW"}],"key":"JjTaf3wVUI"},{"type":"tableCell","children":[{"type":"text","value":"Input data","key":"IRasWN6jIA"}],"key":"l0wwFNXts8"}],"key":"G3v6JIisKx"},{"type":"tableRow","children":[{"type":"tableCell","children":[{"type":"text","value":"MODE","key":"z98HHROqNG"}],"key":"Wq4ftQJcWB"},{"type":"tableCell","children":[{"type":"text","value":"param enum","key":"slDJzPnTct"}],"key":"jAPiX6zjZV"},{"type":"tableCell","children":[{"type":"text","value":"Select operation mode","key":"RZjQRqKsf9"}],"key":"VyUKKME73G"}],"key":"TfvxsCzhMC"},{"type":"tableRow","children":[{"type":"tableCell","children":[{"type":"text","value":"READY","key":"YXTzEYMSRU"}],"key":"htnoyhAXGS"},{"type":"tableCell","children":[{"type":"text","value":"bit_out","key":"bFmxeDvAy8"}],"key":"xSAT0NdyrX"},{"type":"tableCell","children":[{"type":"text","value":"Output Ready","key":"xj2AaAgpYj"}],"key":"h0c694scwH"}],"key":"ZcgUNCgaeT"},{"type":"tableRow","children":[{"type":"tableCell","children":[{"type":"text","value":"OUT","key":"FidfHLEYLj"}],"key":"zlbNL1qwu7"},{"type":"tableCell","children":[{"type":"text","value":"pos_out","key":"mHymg0Lcf2"}],"key":"moldk8Ah8m"},{"type":"tableCell","children":[{"type":"text","value":"Output data","key":"EcW6UyXKnl"}],"key":"BD2e5AHwU9"}],"key":"PVMftsCw9B"},{"type":"tableRow","children":[{"type":"tableCell","children":[{"type":"text","value":"HEALTH","key":"owiap07PUB"}],"key":"BJ8meKbyjM"},{"type":"tableCell","children":[{"type":"text","value":"read enum","key":"z8XZQ9ZfjN"}],"key":"kOIhwcPZ3A"},{"type":"tableCell","children":[{"type":"text","value":"Error","key":"gfzlZQX37n"}],"key":"c8Uv0p0gnR"}],"key":"KhYJPsVxsr"}],"key":"EUV5KS8UE3"},{"type":"heading","depth":2,"position":{"start":{"line":11,"column":1},"end":{"line":11,"column":1}},"children":[{"type":"text","value":"Difference","position":{"start":{"line":11,"column":1},"end":{"line":11,"column":1}},"key":"BwWki1lKqP"}],"identifier":"difference","label":"Difference","html_id":"difference","implicit":true,"key":"nj8lGdyh6z"},{"type":"paragraph","position":{"start":{"line":13,"column":1},"end":{"line":15,"column":1}},"children":[{"type":"text","value":"The difference operation works by latching the value on the input on the rising\nedge of the Enable signal. On a rising edge of the trigger signal the output is\ngiven as the the current input value minus the latched value.","position":{"start":{"line":13,"column":1},"end":{"line":13,"column":1}},"key":"AiZy4weIYl"}],"key":"QtXrF8GeVY"},{"type":"image","url":"/PandABlocks-FPGA/docs/build/91ace76e3fbeafee-f18fd401c6acd1b8f0ee1c179351a481.svg","alt":"Difference mode","class":"dark:hidden","key":"r77C3sZKG7","urlSource":"../../docs/_build/timing/91ace76e3fbeafee.svg"},{"type":"image","url":"/PandABlocks-FPGA/docs/build/91ace76e3fbeafee.dar-5c36a48f77bd07d111c86340fec68720.svg","alt":"Difference mode","class":"hidden dark:block","key":"bvsgX33icx","urlSource":"../../docs/_build/timing/91ace76e3fbeafee.dark.svg"},{"type":"paragraph","position":{"start":{"line":22,"column":1},"end":{"line":23,"column":1}},"children":[{"type":"text","value":"After the operation, the latched value is updated to be the current value on\nthe input.","position":{"start":{"line":22,"column":1},"end":{"line":22,"column":1}},"key":"BI6cYqOjHj"}],"key":"S9l4coK86E"},{"type":"image","url":"/PandABlocks-FPGA/docs/build/44accf07acfb0fb5-35e82e6ff161dcba427b83df3669f488.svg","alt":"Difference mode positive ramping input","class":"dark:hidden","key":"p9VupXgcd7","urlSource":"../../docs/_build/timing/44accf07acfb0fb5.svg"},{"type":"image","url":"/PandABlocks-FPGA/docs/build/44accf07acfb0fb5.dar-9d6d75ee1c6966965074d85915ccdbfa.svg","alt":"Difference mode positive ramping input","class":"hidden dark:block","key":"bXqRHMkrFK","urlSource":"../../docs/_build/timing/44accf07acfb0fb5.dark.svg"},{"type":"paragraph","position":{"start":{"line":29,"column":1},"end":{"line":30,"column":1}},"children":[{"type":"text","value":"The operation continues to work if the current value is less than the latched\nvalue: a negative result is outputted","position":{"start":{"line":29,"column":1},"end":{"line":29,"column":1}},"key":"GgkL524WBq"}],"key":"roTsIGhMzu"},{"type":"image","url":"/PandABlocks-FPGA/docs/build/5eb9f91b4d922132-ba04d6382e7a6589d60a4644cac23031.svg","alt":"Difference mode negative ramping input","class":"dark:hidden","key":"Lp2ojOMoaV","urlSource":"../../docs/_build/timing/5eb9f91b4d922132.svg"},{"type":"image","url":"/PandABlocks-FPGA/docs/build/5eb9f91b4d922132.dar-b88cdaea8cd9916dd2cc8a836f66a083.svg","alt":"Difference mode negative ramping input","class":"hidden dark:block","key":"KZ5dNp7UMw","urlSource":"../../docs/_build/timing/5eb9f91b4d922132.dark.svg"},{"type":"heading","depth":2,"position":{"start":{"line":36,"column":1},"end":{"line":36,"column":1}},"children":[{"type":"text","value":"Average","position":{"start":{"line":36,"column":1},"end":{"line":36,"column":1}},"key":"cD2Ro4cnDM"}],"identifier":"average","label":"Average","html_id":"average","implicit":true,"key":"xoiQCEVVx4"},{"type":"paragraph","position":{"start":{"line":38,"column":1},"end":{"line":40,"column":1}},"children":[{"type":"text","value":"The average function appends a sum value on each clock pulse. When a trigger\nsignal is received it divides the summed value by the number of clock pulses\nthat have passed.","position":{"start":{"line":38,"column":1},"end":{"line":38,"column":1}},"key":"fm1TaiRpJF"}],"key":"pPsmn5T0yN"},{"type":"image","url":"/PandABlocks-FPGA/docs/build/2f81c626e83e79d2-d1b50e4aa20e0ba63bebc7cac0174451.svg","alt":"Average mode summing inputs","class":"dark:hidden","key":"qGEu4RjK2Z","urlSource":"../../docs/_build/timing/2f81c626e83e79d2.svg"},{"type":"image","url":"/PandABlocks-FPGA/docs/build/2f81c626e83e79d2.dar-4939f8e78a704ec174c941fd4ab32f58.svg","alt":"Average mode summing inputs","class":"hidden dark:block","key":"ItgI3yvBWA","urlSource":"../../docs/_build/timing/2f81c626e83e79d2.dark.svg"},{"type":"image","url":"/PandABlocks-FPGA/docs/build/42cea45820e1b02f-8030e6af6d0a4c95376118b770ffb8e0.svg","alt":"Average mode positive ramp","class":"dark:hidden","key":"UqbFIcwmSi","urlSource":"../../docs/_build/timing/42cea45820e1b02f.svg"},{"type":"image","url":"/PandABlocks-FPGA/docs/build/42cea45820e1b02f.dar-b8e1e7a307cdbb96f82d48706e880ad5.svg","alt":"Average mode positive ramp","class":"hidden dark:block","key":"r0g2sbUNrL","urlSource":"../../docs/_build/timing/42cea45820e1b02f.dark.svg"},{"type":"image","url":"/PandABlocks-FPGA/docs/build/e2949337eaa0795f-d226f2563eb0e05a26551b65f72ce979.svg","alt":"Average mode negative ramp","class":"dark:hidden","key":"JyLvWZxpZ2","urlSource":"../../docs/_build/timing/e2949337eaa0795f.svg"},{"type":"image","url":"/PandABlocks-FPGA/docs/build/e2949337eaa0795f.dar-c531a73c3dcde63f96a99a275969368d.svg","alt":"Average mode negative ramp","class":"hidden dark:block","key":"ajclU62fVm","urlSource":"../../docs/_build/timing/e2949337eaa0795f.dark.svg"},{"type":"paragraph","position":{"start":{"line":54,"column":1},"end":{"line":56,"column":1}},"children":[{"type":"text","value":"If a calculation is triggered before the calculation is ready, the system will\nshow an error on the HEALTH output and will then need to be re-enabled before\nanother calculation can be sent.","position":{"start":{"line":54,"column":1},"end":{"line":54,"column":1}},"key":"FrI6J1evlo"}],"key":"dAxM75BR31"},{"type":"image","url":"/PandABlocks-FPGA/docs/build/15d2e2cfdee350a2-295793ad67fa394a5141eeec36c83ff8.svg","alt":"Average mode trigger before calculation ready","class":"dark:hidden","key":"G9qzF9kbRP","urlSource":"../../docs/_build/timing/15d2e2cfdee350a2.svg"},{"type":"image","url":"/PandABlocks-FPGA/docs/build/15d2e2cfdee350a2.dar-c95b388f556551f203fac0ae25a1920c.svg","alt":"Average mode trigger before calculation ready","class":"hidden dark:block","key":"SqVuuhgS4C","urlSource":"../../docs/_build/timing/15d2e2cfdee350a2.dark.svg"},{"type":"image","url":"/PandABlocks-FPGA/docs/build/d62c97af29d1c9a8-4e415b570ab6d39e8082044bcf1ae896.svg","alt":"Zero division","class":"dark:hidden","key":"Dvz3pJXRXr","urlSource":"../../docs/_build/timing/d62c97af29d1c9a8.svg"},{"type":"image","url":"/PandABlocks-FPGA/docs/build/d62c97af29d1c9a8.dar-de0681c3b13d61df11527fc52f015e5d.svg","alt":"Zero division","class":"hidden dark:block","key":"wf4VJYK8Sv","urlSource":"../../docs/_build/timing/d62c97af29d1c9a8.dark.svg"}],"key":"thlqOt1fjK"}],"key":"qkJW9UBepX"},"references":{"cite":{"order":[],"data":{}}},"footer":{"navigation":{"prev":{"title":"FDLY_DO - Fine Delay Digital Output","url":"/fdly-do-doc","group":"PandABlocks-FPGA"},"next":{"title":"FMC_24V - FMC 24V IO Module","url":"/fmc-24v-doc","group":"PandABlocks-FPGA"}}},"domain":"http://localhost:3000"}