{"version":3,"kind":"Article","sha256":"eef80135a5a634237b7d8028ab3bc9a404d54edb444243bf39332bfb698a2eae","slug":"sfp-panda-sync-doc","location":"/../modules/sfp_panda_sync/sfp_panda_sync_doc.md","dependencies":[],"frontmatter":{"title":"SFP_PANDA_SYNC - Synchronize data between 2 PandAs","content_includes_title":false,"github":"https://github.com/PandABlocks/PandABlocks-FPGA","numbering":{"title":{"offset":2}},"source_url":"https://github.com/PandABlocks/PandABlocks-FPGA/blob/main/modules/sfp_panda_sync/sfp_panda_sync_doc.md","edit_url":"https://github.com/PandABlocks/PandABlocks-FPGA/edit/main/modules/sfp_panda_sync/sfp_panda_sync_doc.md","exports":[{"format":"md","filename":"sfp_panda_sync_doc.md","url":"/PandABlocks-FPGA/docs/build/sfp_panda_sync_doc-133647099ece79d1ff0b2fb738ef5df8.md"}]},"mdast":{"type":"root","children":[{"type":"block","children":[{"type":"heading","depth":2,"position":{"start":{"line":3,"column":1},"end":{"line":3,"column":1}},"children":[{"type":"text","value":"Fields","position":{"start":{"line":3,"column":1},"end":{"line":3,"column":1}},"key":"pb4ipSAXw6"}],"identifier":"fields","label":"Fields","html_id":"fields","implicit":true,"key":"RkOnLFsY6H"},{"type":"table","children":[{"type":"tableRow","children":[{"type":"tableCell","children":[{"type":"text","value":"Name","key":"k79Z3TPyYc"}],"header":true,"key":"L9zXsYADTj"},{"type":"tableCell","children":[{"type":"text","value":"Type","key":"gScbzHP0N5"}],"header":true,"key":"Ihipdd1kMQ"},{"type":"tableCell","children":[{"type":"text","value":"Description","key":"fO7AYAjDz6"}],"header":true,"key":"tmFFW7X4x7"}],"key":"lrj1MEgbjC"},{"type":"tableRow","children":[{"type":"tableCell","children":[{"type":"text","value":"IN.SYNC_RESET","key":"udoMe0g151"}],"key":"NOsXgraniq"},{"type":"tableCell","children":[{"type":"text","value":"write action","key":"JBcmyMyVfj"}],"key":"RZ6H9uFASV"},{"type":"tableCell","children":[{"type":"text","value":"Local reset","key":"FWgzKfNPd5"}],"key":"WS8jlChopC"}],"key":"SPMJEz6Kj8"},{"type":"tableRow","children":[{"type":"tableCell","children":[{"type":"text","value":"IN.LINKUP","key":"Ub00grh4OP"}],"key":"CRXc4ufkkY"},{"type":"tableCell","children":[{"type":"text","value":"read","key":"HTw9Wnif83"}],"key":"W9LheWZRCI"},{"type":"tableCell","children":[{"type":"text","value":"GTX link status","key":"d4XWGwtWGO"}],"key":"vhrc7BtsJb"}],"key":"FsZH4N62yT"},{"type":"tableRow","children":[{"type":"tableCell","children":[{"type":"text","value":"IN.BIT1","key":"tvOUNrorV7"}],"key":"brKPUVFx6c"},{"type":"tableCell","children":[{"type":"text","value":"bit_out","key":"QlW1hF9lU9"}],"key":"AN6kKqFBPJ"},{"type":"tableCell","children":[{"type":"text","value":"SFP panda sync bit 1 input","key":"Z6Claks3zT"}],"key":"BvrwukPaoi"}],"key":"bmapuCtVyM"},{"type":"tableRow","children":[{"type":"tableCell","children":[{"type":"text","value":"IN.BIT2","key":"l9uJrIgGBS"}],"key":"eKrtJh10O5"},{"type":"tableCell","children":[{"type":"text","value":"bit_out","key":"QHtAl0pBqx"}],"key":"UOxnBKiMVV"},{"type":"tableCell","children":[{"type":"text","value":"SFP panda sync bit 2 input","key":"GrgxprwQnA"}],"key":"YErAh8bbEH"}],"key":"yAYGDM8E7k"},{"type":"tableRow","children":[{"type":"tableCell","children":[{"type":"text","value":"IN.BIT3","key":"uqzr16O42u"}],"key":"pLlkDs1zLi"},{"type":"tableCell","children":[{"type":"text","value":"bit_out","key":"nnBSj3YlqC"}],"key":"OxNJp1qkJ7"},{"type":"tableCell","children":[{"type":"text","value":"SFP panda sync bit 3 input","key":"LZw3qQ5PDS"}],"key":"KmH2lzBPYr"}],"key":"VREJuQ1Hfy"},{"type":"tableRow","children":[{"type":"tableCell","children":[{"type":"text","value":"IN.BIT4","key":"b8u7GI1ZfK"}],"key":"Yro59ywyWb"},{"type":"tableCell","children":[{"type":"text","value":"bit_out","key":"cgcAsqWAMm"}],"key":"rQ7snX01cI"},{"type":"tableCell","children":[{"type":"text","value":"SFP panda sync bit 4 input","key":"i1cjOqycmV"}],"key":"mNi5MrHD2j"}],"key":"ao5HPgEKHE"},{"type":"tableRow","children":[{"type":"tableCell","children":[{"type":"text","value":"IN.BIT5","key":"GgVMEsoIJb"}],"key":"p8mpnDk8Lz"},{"type":"tableCell","children":[{"type":"text","value":"bit_out","key":"GiyDPqlPDw"}],"key":"MfuT0mwDGJ"},{"type":"tableCell","children":[{"type":"text","value":"SFP panda sync bit 5 input","key":"PUk8Siaevz"}],"key":"fek8kRtFgZ"}],"key":"Y08n4c1OFb"},{"type":"tableRow","children":[{"type":"tableCell","children":[{"type":"text","value":"IN.BIT6","key":"OfkS91rskS"}],"key":"aOQUVKWg4T"},{"type":"tableCell","children":[{"type":"text","value":"bit_out","key":"qprpv7iBCK"}],"key":"crIHqvzjs6"},{"type":"tableCell","children":[{"type":"text","value":"SFP panda sync bit 6 input","key":"mDDSl2DFEW"}],"key":"qXphb6msvh"}],"key":"Tb60yO1i6B"},{"type":"tableRow","children":[{"type":"tableCell","children":[{"type":"text","value":"IN.BIT7","key":"wp64oYBtpH"}],"key":"DnoHsMJfH6"},{"type":"tableCell","children":[{"type":"text","value":"bit_out","key":"WLjMbMl437"}],"key":"SegHHN31x8"},{"type":"tableCell","children":[{"type":"text","value":"SFP panda sync bit 7 input","key":"quFSaoHiY8"}],"key":"K9IHGelqiQ"}],"key":"kjKciDTyfC"},{"type":"tableRow","children":[{"type":"tableCell","children":[{"type":"text","value":"IN.BIT8","key":"ytkCBnTOqF"}],"key":"pA1gecvmvS"},{"type":"tableCell","children":[{"type":"text","value":"bit_out","key":"fEepkziJuT"}],"key":"Dq2JmQh6GF"},{"type":"tableCell","children":[{"type":"text","value":"SFP panda sync bit 8 input","key":"eP0ukBI3rv"}],"key":"ugMekJd4v2"}],"key":"KjShyvqkoY"},{"type":"tableRow","children":[{"type":"tableCell","children":[{"type":"text","value":"IN.POS1","key":"RaEzH9m8by"}],"key":"lPrDBHsIo2"},{"type":"tableCell","children":[{"type":"text","value":"pos_out","key":"i3NH71CoPV"}],"key":"oV4aBbMyhE"},{"type":"tableCell","children":[{"type":"text","value":"SFP panda sync pos 1 input","key":"W9aLP8YVq9"}],"key":"cnjth9axq3"}],"key":"JS1i5oOyJ3"},{"type":"tableRow","children":[{"type":"tableCell","children":[{"type":"text","value":"IN.POS2","key":"jh7dc8DPXg"}],"key":"KRhrjs8yQY"},{"type":"tableCell","children":[{"type":"text","value":"pos_out","key":"txmNYtQBvP"}],"key":"nqnJFCFVnl"},{"type":"tableCell","children":[{"type":"text","value":"SFP panda sync pos 2 input","key":"VoEwzBxyOL"}],"key":"fuiQAF9lY3"}],"key":"TE4wKfVXK3"},{"type":"tableRow","children":[{"type":"tableCell","children":[{"type":"text","value":"IN.POS3","key":"t5QTKOeAOu"}],"key":"brLoKD4ciD"},{"type":"tableCell","children":[{"type":"text","value":"pos_out","key":"VOLURujdKK"}],"key":"nzwnKrC6jd"},{"type":"tableCell","children":[{"type":"text","value":"SFP panda sync pos 3 input","key":"ah5fUyhjRj"}],"key":"zsH5fedf8Z"}],"key":"hfVVmUH2VA"},{"type":"tableRow","children":[{"type":"tableCell","children":[{"type":"text","value":"IN.POS4","key":"CaCkD0UusX"}],"key":"JHW9zmRHR3"},{"type":"tableCell","children":[{"type":"text","value":"pos_out","key":"rXZqf6b4fi"}],"key":"WI1rhvfb0D"},{"type":"tableCell","children":[{"type":"text","value":"SFP panda sync pos 4 input","key":"rMfm11TWe5"}],"key":"xCFJ31cju1"}],"key":"q6QEjDw2LJ"},{"type":"tableRow","children":[{"type":"tableCell","children":[{"type":"text","value":"IN.HEALTH","key":"js4HldlxCr"}],"key":"wCnQTCcn6S"},{"type":"tableCell","children":[{"type":"text","value":"read enum","key":"xwccEmmwx1"}],"key":"AGFMye91ct"},{"type":"tableCell","children":[{"type":"text","value":"Error status","key":"aXh5eLS5u9"}],"key":"A63gfbcidX"}],"key":"SoXX941r7o"},{"type":"tableRow","children":[{"type":"tableCell","children":[{"type":"text","value":"IN.ERR_CNT","key":"jpxUBFFRRS"}],"key":"DSp0pu1lfZ"},{"type":"tableCell","children":[{"type":"text","value":"read uint","key":"pkR6asgK6w"}],"key":"JXLrrcXEgY"},{"type":"tableCell","children":[{"type":"text","value":"Number of not-in-table or disparity errors","key":"nJn9LUJYX0"}],"key":"QZkUL9k7qq"}],"key":"hnxThRE5qZ"},{"type":"tableRow","children":[{"type":"tableCell","children":[{"type":"text","value":"OUT.MGT_RESET","key":"HnyxCA5tpT"}],"key":"G9S6E2gvwc"},{"type":"tableCell","children":[{"type":"text","value":"write action","key":"CNHOVIRmNL"}],"key":"EqKc1jO0Nr"},{"type":"tableCell","children":[{"type":"text","value":"MGT hard reset","key":"FpnIaZLBRR"}],"key":"RXZy3av91g"}],"key":"Nqerj53MND"},{"type":"tableRow","children":[{"type":"tableCell","children":[{"type":"text","value":"OUT.BIT1","key":"kOPUM1XQKv"}],"key":"W2YEVJrKqm"},{"type":"tableCell","children":[{"type":"text","value":"bit_mux","key":"kU8ICHlsP9"}],"key":"iUNwztM7ea"},{"type":"tableCell","children":[{"type":"text","value":"SFP panda sync bit 1 output","key":"IChfxNPcU0"}],"key":"hDc7xbUZEW"}],"key":"sXWnhSklZM"},{"type":"tableRow","children":[{"type":"tableCell","children":[{"type":"text","value":"OUT.BIT2","key":"QU51Xylycd"}],"key":"rzS3UOfYhk"},{"type":"tableCell","children":[{"type":"text","value":"bit_mux","key":"JivPFBtGIY"}],"key":"s6M5gW2Yu8"},{"type":"tableCell","children":[{"type":"text","value":"SFP panda sync bit 2 output","key":"NwxpEBSN46"}],"key":"caa8LM2jTR"}],"key":"aqvQyDx5Fn"},{"type":"tableRow","children":[{"type":"tableCell","children":[{"type":"text","value":"OUT.BIT3","key":"soadnZyz5T"}],"key":"AGIL63RwJK"},{"type":"tableCell","children":[{"type":"text","value":"bit_mux","key":"HcHqHlbHRY"}],"key":"EIZtSuKuSE"},{"type":"tableCell","children":[{"type":"text","value":"SFP panda sync bit 3 output","key":"bD8cwOZQyR"}],"key":"n09YbElSNT"}],"key":"ILRIwLgrQa"},{"type":"tableRow","children":[{"type":"tableCell","children":[{"type":"text","value":"OUT.BIT4","key":"IVptMsLbI5"}],"key":"oiml0OT6k4"},{"type":"tableCell","children":[{"type":"text","value":"bit_mux","key":"fEweA4uH2f"}],"key":"Wrxnh584so"},{"type":"tableCell","children":[{"type":"text","value":"SFP panda sync bit 4 output","key":"Gr8XZ0kJs5"}],"key":"DK9JN1fqqN"}],"key":"qLVMpzlwQg"},{"type":"tableRow","children":[{"type":"tableCell","children":[{"type":"text","value":"OUT.BIT5","key":"zjjjqDQ4x5"}],"key":"TEDFVEmpIk"},{"type":"tableCell","children":[{"type":"text","value":"bit_mux","key":"OTViSAoYeg"}],"key":"FKIZd0GB8A"},{"type":"tableCell","children":[{"type":"text","value":"SFP panda sync bit 5 output","key":"aALbminbLU"}],"key":"dG1uazGMSk"}],"key":"lP5Spp7w2m"},{"type":"tableRow","children":[{"type":"tableCell","children":[{"type":"text","value":"OUT.BIT6","key":"kfDKtkix7t"}],"key":"U0A2E0kKrB"},{"type":"tableCell","children":[{"type":"text","value":"bit_mux","key":"GMbHfMfUJj"}],"key":"tKa3rA46ZC"},{"type":"tableCell","children":[{"type":"text","value":"SFP panda sync bit 6 output","key":"R90QY8qbNa"}],"key":"kSYjQ49ffr"}],"key":"xPEuU8SxsW"},{"type":"tableRow","children":[{"type":"tableCell","children":[{"type":"text","value":"OUT.BIT7","key":"Jnxd0JLGdk"}],"key":"JF0GcBvQGH"},{"type":"tableCell","children":[{"type":"text","value":"bit_mux","key":"KHV21RJiwv"}],"key":"hNvhtygQqq"},{"type":"tableCell","children":[{"type":"text","value":"SFP panda sync bit 7 output","key":"eqZTNL3qjS"}],"key":"Esnm2LcrdO"}],"key":"kd76e4lWd6"},{"type":"tableRow","children":[{"type":"tableCell","children":[{"type":"text","value":"OUT.BIT8","key":"Q0Gw6kLufz"}],"key":"I2iqZWnyFF"},{"type":"tableCell","children":[{"type":"text","value":"bit_mux","key":"n4mzDW2hBV"}],"key":"w2ePfVkrRa"},{"type":"tableCell","children":[{"type":"text","value":"SFP panda sync bit 8 output","key":"KNxdKnsE1A"}],"key":"AHwrmz0uyL"}],"key":"wYHJO7RLah"},{"type":"tableRow","children":[{"type":"tableCell","children":[{"type":"text","value":"OUT.POS1","key":"el1nkJIdTO"}],"key":"SQFMKFIXE8"},{"type":"tableCell","children":[{"type":"text","value":"pos_mux","key":"mhx61pL0vQ"}],"key":"W9vyumnnF7"},{"type":"tableCell","children":[{"type":"text","value":"SFP panda sync pos 1 output","key":"yjO4eVLr30"}],"key":"PRNSxKmOlC"}],"key":"xksSi4B6ys"},{"type":"tableRow","children":[{"type":"tableCell","children":[{"type":"text","value":"OUT.POS2","key":"lX2RKgVe5c"}],"key":"jLUhZHAvoC"},{"type":"tableCell","children":[{"type":"text","value":"pos_mux","key":"SW7W3MgEdQ"}],"key":"E76iMoOvoW"},{"type":"tableCell","children":[{"type":"text","value":"SFP panda sync pos 2 output","key":"e6dmIFNN8P"}],"key":"gU5BJeoarE"}],"key":"iK5y8JDdau"},{"type":"tableRow","children":[{"type":"tableCell","children":[{"type":"text","value":"OUT.POS3","key":"h0ujUKNGbB"}],"key":"Wyoqiyf6vE"},{"type":"tableCell","children":[{"type":"text","value":"pos_mux","key":"hFmNemFed0"}],"key":"KjrBfYuDa9"},{"type":"tableCell","children":[{"type":"text","value":"SFP panda sync pos 3 output","key":"lYiK0oep1u"}],"key":"RLNBGBVyYI"}],"key":"go0pjqxSMB"},{"type":"tableRow","children":[{"type":"tableCell","children":[{"type":"text","value":"OUT.POS4","key":"mIRQXhTiJ7"}],"key":"E0VHo6awod"},{"type":"tableCell","children":[{"type":"text","value":"pos_mux","key":"ShNoc1FYa3"}],"key":"IqfrI5Pxdp"},{"type":"tableCell","children":[{"type":"text","value":"SFP panda sync pos 4 output","key":"lgAwImYPGn"}],"key":"ON6z3lkKMB"}],"key":"sEIMOMkGwZ"}],"key":"sV7a2z76nC"}],"key":"iaqvQxUilp"}],"key":"HNDt3oEyli"},"references":{"cite":{"order":[],"data":{}}},"footer":{"navigation":{"prev":{"title":"SFP_LOOPBACK- SFP Loopback Module","url":"/sfp-loopback-doc","group":"PandABlocks-FPGA"},"next":{"title":"SFP_UDPONTRIG - SFP UDP on trig Module","url":"/sfp-udpontrig-doc","group":"PandABlocks-FPGA"}}},"domain":"http://localhost:3000"}