{"version":3,"kind":"Article","sha256":"84bd149b26357a904ac72e673ea5183f8ef3609afb3aafbccb76a3efc79f3346","slug":"srgate-doc","location":"/../modules/srgate/srgate_doc.md","dependencies":[],"frontmatter":{"title":"SRGATE - Set Reset Gate","content_includes_title":false,"github":"https://github.com/PandABlocks/PandABlocks-FPGA","numbering":{"title":{"offset":2}},"source_url":"https://github.com/PandABlocks/PandABlocks-FPGA/blob/main/modules/srgate/srgate_doc.md","edit_url":"https://github.com/PandABlocks/PandABlocks-FPGA/edit/main/modules/srgate/srgate_doc.md","thumbnail":"/PandABlocks-FPGA/docs/build/9646a181614292ef-d51241a04899bf7e90a4c2697fc6bf82.svg","exports":[{"format":"md","filename":"srgate_doc.md","url":"/PandABlocks-FPGA/docs/build/srgate_doc-fa8af94ec6d5f46456c83e462978c00e.md"}]},"mdast":{"type":"root","children":[{"type":"block","children":[{"type":"paragraph","position":{"start":{"line":3,"column":1},"end":{"line":6,"column":1}},"children":[{"type":"text","value":"An SRGATE block produces either a high (SET) or low (RST) output. It has\nconfigurable inputs and an option to force its output independently. Both Set\nand Rst inputs can be selected from bit bus, and the active-edge of its\ninputs is configurable. An enable signal allows the block to ignore its inputs.","position":{"start":{"line":3,"column":1},"end":{"line":3,"column":1}},"key":"cbL4wNatmH"}],"key":"vvxqpSZJIt"},{"type":"heading","depth":2,"position":{"start":{"line":9,"column":1},"end":{"line":9,"column":1}},"children":[{"type":"text","value":"Fields","position":{"start":{"line":9,"column":1},"end":{"line":9,"column":1}},"key":"VRECD20ADE"}],"identifier":"fields","label":"Fields","html_id":"fields","implicit":true,"key":"UujeHDBXtK"},{"type":"table","children":[{"type":"tableRow","children":[{"type":"tableCell","children":[{"type":"text","value":"Name","key":"qQlxb4rhqH"}],"header":true,"key":"v4P1xwofg5"},{"type":"tableCell","children":[{"type":"text","value":"Type","key":"lfC8XcPHFU"}],"header":true,"key":"lBwb7eLTq2"},{"type":"tableCell","children":[{"type":"text","value":"Description","key":"vfuzJqlita"}],"header":true,"key":"SaAvGOucs2"}],"key":"sQ0p0KPrWO"},{"type":"tableRow","children":[{"type":"tableCell","children":[{"type":"text","value":"ENABLE","key":"iD5XhLlY4T"}],"key":"zzyVycJxvw"},{"type":"tableCell","children":[{"type":"text","value":"bit_mux","key":"CJTVUiWDrx"}],"key":"k5sJ21o72o"},{"type":"tableCell","children":[{"type":"text","value":"Whether to listen to SET/RST events","key":"V0HlJ5JYf8"}],"key":"FTZtO24s3d"}],"key":"GBCjhKZnd7"},{"type":"tableRow","children":[{"type":"tableCell","children":[{"type":"text","value":"SET","key":"IudOiVKpdu"}],"key":"J96zwGo7yh"},{"type":"tableCell","children":[{"type":"text","value":"bit_mux","key":"oTIYg5JBVv"}],"key":"cJjt7tiB2a"},{"type":"tableCell","children":[{"type":"text","value":"A falling/rising edge sets the output to 1","key":"LVoT0bXRPg"}],"key":"q4dcTvMO5A"}],"key":"DnLJZZI7zV"},{"type":"tableRow","children":[{"type":"tableCell","children":[{"type":"text","value":"RST","key":"UXvXaOIlha"}],"key":"LI9bVL0OOa"},{"type":"tableCell","children":[{"type":"text","value":"bit_mux","key":"KvwVWETjUr"}],"key":"lvbmi9Rf45"},{"type":"tableCell","children":[{"type":"text","value":"a falling/rising edge resets the output to 0","key":"iGcEfPxQjQ"}],"key":"vtcVD7DurY"}],"key":"Ql06Uqrscm"},{"type":"tableRow","children":[{"type":"tableCell","children":[{"type":"text","value":"WHEN_DISABLED","key":"vCXmZ5gX6c"}],"key":"VojyWh3ZwU"},{"type":"tableCell","children":[{"type":"text","value":"param enum","key":"rOmKvZW8b4"}],"key":"FNS87QeWPI"},{"type":"tableCell","children":[{"type":"text","value":"What to do with the output when Enable is low","key":"vIwpleQ1AP"}],"key":"KFaaKFptPV"}],"key":"ggN5nhhN8y"},{"type":"tableRow","children":[{"type":"tableCell","children":[{"type":"text","value":"SET_EDGE","key":"NIoKl1T6zJ"}],"key":"Y9Ud4OsX9f"},{"type":"tableCell","children":[{"type":"text","value":"param enum","key":"E9c5GZYIJc"}],"key":"fvqlp7Blv4"},{"type":"tableCell","children":[{"type":"text","value":"Output set edge","key":"S3Y0VmS5U7"}],"key":"n7DuhjRlYP"}],"key":"Vc9oAeEtoh"},{"type":"tableRow","children":[{"type":"tableCell","children":[{"type":"text","value":"RST_EDGE","key":"q4aeuzuKre"}],"key":"sVwlPLUjUw"},{"type":"tableCell","children":[{"type":"text","value":"param enum","key":"fTqYZpTzgm"}],"key":"A7NtTDGplE"},{"type":"tableCell","children":[{"type":"text","value":"Output reset edge","key":"qM4RyzjJ8b"}],"key":"yIzJ8Rn2tu"}],"key":"h4WNZ1C9J7"},{"type":"tableRow","children":[{"type":"tableCell","children":[{"type":"text","value":"FORCE_SET","key":"gCjcmnEIIH"}],"key":"ip3MMYf2V5"},{"type":"tableCell","children":[{"type":"text","value":"write action","key":"k6gbGFpZKC"}],"key":"PaH9rIxjE5"},{"type":"tableCell","children":[{"type":"text","value":"Set output to 1","key":"lUc1Ecs5pT"}],"key":"CbgLotgDQu"}],"key":"i0F0cO59L7"},{"type":"tableRow","children":[{"type":"tableCell","children":[{"type":"text","value":"FORCE_RST","key":"LY20b2Rj0M"}],"key":"lnDrw8WL0W"},{"type":"tableCell","children":[{"type":"text","value":"write action","key":"snfu77CJsV"}],"key":"TCfWJNlApn"},{"type":"tableCell","children":[{"type":"text","value":"Reset output to 0","key":"NQ86IFKLou"}],"key":"FFCbTk1i3q"}],"key":"TWLZSmukfA"},{"type":"tableRow","children":[{"type":"tableCell","children":[{"type":"text","value":"OUT","key":"BsOjM4U5xk"}],"key":"Vdy06VinIp"},{"type":"tableCell","children":[{"type":"text","value":"bit_out","key":"Fl5FY55LU5"}],"key":"xFL5Eakq7Y"},{"type":"tableCell","children":[{"type":"text","value":"output value","key":"BAb4O9roDf"}],"key":"UGitP3mZdB"}],"key":"SXijFIye8T"}],"key":"XYw42QCPjk"},{"type":"heading","depth":2,"position":{"start":{"line":12,"column":1},"end":{"line":12,"column":1}},"children":[{"type":"text","value":"Normal conditions","position":{"start":{"line":12,"column":1},"end":{"line":12,"column":1}},"key":"pE1riZetXl"}],"identifier":"normal-conditions","label":"Normal conditions","html_id":"normal-conditions","implicit":true,"key":"a69SbisvQa"},{"type":"paragraph","position":{"start":{"line":14,"column":1},"end":{"line":15,"column":1}},"children":[{"type":"text","value":"The normal behaviour is to set the output OUT on the configured edge of the\nSET or RESET input.","position":{"start":{"line":14,"column":1},"end":{"line":14,"column":1}},"key":"VGKLdIWI2S"}],"key":"gHUHhy2aOs"},{"type":"image","url":"/PandABlocks-FPGA/docs/build/9646a181614292ef-d51241a04899bf7e90a4c2697fc6bf82.svg","alt":"Set on rising Edge","class":"dark:hidden","key":"rYf5kShoXD","urlSource":"../../docs/_build/timing/9646a181614292ef.svg"},{"type":"image","url":"/PandABlocks-FPGA/docs/build/9646a181614292ef.dar-be04c621d1f5397d4bce075063312750.svg","alt":"Set on rising Edge","class":"hidden dark:block","key":"y0o73iV4WR","urlSource":"../../docs/_build/timing/9646a181614292ef.dark.svg"},{"type":"image","url":"/PandABlocks-FPGA/docs/build/925edae353701d4a-dec30a3c7a5b82fe189849619fa71e02.svg","alt":"Set on falling Edge","class":"dark:hidden","key":"YJgrjv1l65","urlSource":"../../docs/_build/timing/925edae353701d4a.svg"},{"type":"image","url":"/PandABlocks-FPGA/docs/build/925edae353701d4a.dar-e8bfd5702c05ac61b5cb3513404b8dbe.svg","alt":"Set on falling Edge","class":"hidden dark:block","key":"wH8nLZCEqt","urlSource":"../../docs/_build/timing/925edae353701d4a.dark.svg"},{"type":"image","url":"/PandABlocks-FPGA/docs/build/2fb7be832f725c4b-6661a8af59f91afa5a8a7c6c31c14113.svg","alt":"Set on either Edge RST default","class":"dark:hidden","key":"Y3D0EUViB9","urlSource":"../../docs/_build/timing/2fb7be832f725c4b.svg"},{"type":"image","url":"/PandABlocks-FPGA/docs/build/2fb7be832f725c4b.dar-fb84dd60cb277631afba356bfcf49d0f.svg","alt":"Set on either Edge RST default","class":"hidden dark:block","key":"kDKbR8fnm1","urlSource":"../../docs/_build/timing/2fb7be832f725c4b.dark.svg"},{"type":"image","url":"/PandABlocks-FPGA/docs/build/321f4aff401c3167-9642622bab3bb705b51961fb849e92f8.svg","alt":"Reset on rising Edge","class":"dark:hidden","key":"uicuTdU1rc","urlSource":"../../docs/_build/timing/321f4aff401c3167.svg"},{"type":"image","url":"/PandABlocks-FPGA/docs/build/321f4aff401c3167.dar-64ef1691884a2b7fcf724868f762d4b2.svg","alt":"Reset on rising Edge","class":"hidden dark:block","key":"jh6km6G7ix","urlSource":"../../docs/_build/timing/321f4aff401c3167.dark.svg"},{"type":"image","url":"/PandABlocks-FPGA/docs/build/9e6835ed30175cbf-0d901c666407089ddbf3ea7fadd68a0f.svg","alt":"Reset on falling Edge","class":"dark:hidden","key":"UEqJXFT5pM","urlSource":"../../docs/_build/timing/9e6835ed30175cbf.svg"},{"type":"image","url":"/PandABlocks-FPGA/docs/build/9e6835ed30175cbf.dar-0861b2bffd18c067835c563fa37b9a4b.svg","alt":"Reset on falling Edge","class":"hidden dark:block","key":"MgNeJunVVF","urlSource":"../../docs/_build/timing/9e6835ed30175cbf.dark.svg"},{"type":"image","url":"/PandABlocks-FPGA/docs/build/4c92bfb7669b9a69-d5b6e2921496d643c726c505880c086b.svg","alt":"Reset on either Edge SET falling","class":"dark:hidden","key":"ONCJrjgxNZ","urlSource":"../../docs/_build/timing/4c92bfb7669b9a69.svg"},{"type":"image","url":"/PandABlocks-FPGA/docs/build/4c92bfb7669b9a69.dar-02219bfc1e09c96a25f95bc9a4e42861.svg","alt":"Reset on either Edge SET falling","class":"hidden dark:block","key":"W1a98oxCfX","urlSource":"../../docs/_build/timing/4c92bfb7669b9a69.dark.svg"},{"type":"heading","depth":2,"position":{"start":{"line":41,"column":1},"end":{"line":41,"column":1}},"children":[{"type":"text","value":"Disabling the block","position":{"start":{"line":41,"column":1},"end":{"line":41,"column":1}},"key":"p5QvK4fvwK"}],"identifier":"disabling-the-block","label":"Disabling the block","html_id":"disabling-the-block","implicit":true,"key":"b0Q5hErysu"},{"type":"paragraph","position":{"start":{"line":42,"column":1},"end":{"line":43,"column":1}},"children":[{"type":"text","value":"The default behaviour is to force the block output low when disabled, ignoring\nany SET/RST events:","position":{"start":{"line":42,"column":1},"end":{"line":42,"column":1}},"key":"rclkZC6A6g"}],"key":"pyZEfGld87"},{"type":"image","url":"/PandABlocks-FPGA/docs/build/d2225894031756af-2881bea8cb9baaf1387127cef2daa738.svg","alt":"Output low while disabled","class":"dark:hidden","key":"iwpUL8xaTS","urlSource":"../../docs/_build/timing/d2225894031756af.svg"},{"type":"image","url":"/PandABlocks-FPGA/docs/build/d2225894031756af.dar-7b52673e52b3e0c7e4f0983f42a35e6b.svg","alt":"Output low while disabled","class":"hidden dark:block","key":"eFWEnPZx0y","urlSource":"../../docs/_build/timing/d2225894031756af.dark.svg"},{"type":"paragraph","position":{"start":{"line":49,"column":1},"end":{"line":49,"column":1}},"children":[{"type":"text","value":"The disabled value can also be set high:","position":{"start":{"line":49,"column":1},"end":{"line":49,"column":1}},"key":"BHLHIQbcEi"}],"key":"nB4ISJRMlv"},{"type":"image","url":"/PandABlocks-FPGA/docs/build/62a9a200f5ed043e-07cb0fef25066711b97a0328ac15931d.svg","alt":"Output high while disabled","class":"dark:hidden","key":"mQEeePZJDr","urlSource":"../../docs/_build/timing/62a9a200f5ed043e.svg"},{"type":"image","url":"/PandABlocks-FPGA/docs/build/62a9a200f5ed043e.dar-87dfdaba8371a4e323bc4ed2417c7d8a.svg","alt":"Output high while disabled","class":"hidden dark:block","key":"foRbUSlYT0","urlSource":"../../docs/_build/timing/62a9a200f5ed043e.dark.svg"},{"type":"paragraph","position":{"start":{"line":55,"column":1},"end":{"line":55,"column":1}},"children":[{"type":"text","value":"Or left at its current value:","position":{"start":{"line":55,"column":1},"end":{"line":55,"column":1}},"key":"cvaXzQ2XW0"}],"key":"tFYJio2VqW"},{"type":"image","url":"/PandABlocks-FPGA/docs/build/4bb76be21aa6200a-f9144316048a6962a2a9bf4a4f8c3372.svg","alt":"Output left at current while disabled","class":"dark:hidden","key":"gB2WbIhx3y","urlSource":"../../docs/_build/timing/4bb76be21aa6200a.svg"},{"type":"image","url":"/PandABlocks-FPGA/docs/build/4bb76be21aa6200a.dar-cfbf8b6a2c073f2766e40911a8927259.svg","alt":"Output left at current while disabled","class":"hidden dark:block","key":"cVIngaCfSW","urlSource":"../../docs/_build/timing/4bb76be21aa6200a.dark.svg"},{"type":"heading","depth":2,"position":{"start":{"line":61,"column":1},"end":{"line":61,"column":1}},"children":[{"type":"text","value":"Active edge configure conditions","position":{"start":{"line":61,"column":1},"end":{"line":61,"column":1}},"key":"xa4XVTKTvC"}],"identifier":"active-edge-configure-conditions","label":"Active edge configure conditions","html_id":"active-edge-configure-conditions","implicit":true,"key":"teBaNhePND"},{"type":"paragraph","position":{"start":{"line":62,"column":1},"end":{"line":64,"column":1}},"children":[{"type":"text","value":"if the active edge is ‘rising’ then reset to ‘falling’ at the same time as a\nrising edge on the SET input, the block will ignore the rising edge and set\nthe output OUT on the falling edge of the SET input.","position":{"start":{"line":62,"column":1},"end":{"line":62,"column":1}},"key":"kDawAvfCQw"}],"key":"GqhBKHzU7y"},{"type":"image","url":"/PandABlocks-FPGA/docs/build/a9fb48612b016ae2-086757b6202b47d2b249375924851b45.svg","alt":"Rising SET with SET_EDGE reconfigure","class":"dark:hidden","key":"JmjzVaQ0ml","urlSource":"../../docs/_build/timing/a9fb48612b016ae2.svg"},{"type":"image","url":"/PandABlocks-FPGA/docs/build/a9fb48612b016ae2.dar-4d8d05a3f325d9d5fbdeb70a3719e34b.svg","alt":"Rising SET with SET_EDGE reconfigure","class":"hidden dark:block","key":"Q7QpxSpvj4","urlSource":"../../docs/_build/timing/a9fb48612b016ae2.dark.svg"},{"type":"paragraph","position":{"start":{"line":70,"column":1},"end":{"line":71,"column":1}},"children":[{"type":"text","value":"If the active edge changes to ‘falling’  at the same time as a falling edge\non the SET input, the output OUT will be set following this.","position":{"start":{"line":70,"column":1},"end":{"line":70,"column":1}},"key":"n2qzPOUyIr"}],"key":"ROkx8v9h7n"},{"type":"image","url":"/PandABlocks-FPGA/docs/build/f7ff59155bc82a47-7eafbfd7f630cdd5b96e3fa941a7929b.svg","alt":"Falling SET with SET_EDGE reconfigure","class":"dark:hidden","key":"e7v5qP4QZl","urlSource":"../../docs/_build/timing/f7ff59155bc82a47.svg"},{"type":"image","url":"/PandABlocks-FPGA/docs/build/f7ff59155bc82a47.dar-691a5d548730963132ae1796f14a6d50.svg","alt":"Falling SET with SET_EDGE reconfigure","class":"hidden dark:block","key":"Z9MPvSwOmN","urlSource":"../../docs/_build/timing/f7ff59155bc82a47.dark.svg"},{"type":"image","url":"/PandABlocks-FPGA/docs/build/08adcd493e84ae7b-9b99874a50c85dbab0472a2c2656dcc2.svg","alt":"Falling RST with with reset edge reconfigure","class":"dark:hidden","key":"bWjROJZMKP","urlSource":"../../docs/_build/timing/08adcd493e84ae7b.svg"},{"type":"image","url":"/PandABlocks-FPGA/docs/build/08adcd493e84ae7b.dar-28d08c43a8ae4827adf1bc546307ffc7.svg","alt":"Falling RST with with reset edge reconfigure","class":"hidden dark:block","key":"laYYHbWzLB","urlSource":"../../docs/_build/timing/08adcd493e84ae7b.dark.svg"},{"type":"heading","depth":2,"position":{"start":{"line":81,"column":1},"end":{"line":81,"column":1}},"children":[{"type":"text","value":"Set-reset conditions","position":{"start":{"line":81,"column":1},"end":{"line":81,"column":1}},"key":"ZctiGV6aHu"}],"identifier":"set-reset-conditions","label":"Set-reset conditions","html_id":"set-reset-conditions","implicit":true,"key":"Ch8BbbtGTH"},{"type":"paragraph","position":{"start":{"line":83,"column":1},"end":{"line":85,"column":1}},"children":[{"type":"text","value":"When determining the output if two values are set simultaneously, FORCE_SET and\nFORCE_RESET registers take priority over the input bus, and reset takes priority\nover set.","position":{"start":{"line":83,"column":1},"end":{"line":83,"column":1}},"key":"myiMN9yXeJ"}],"key":"WMTpuXDwKB"},{"type":"image","url":"/PandABlocks-FPGA/docs/build/b4a792925037cd4f-1816dc4ac4e4cd5bd2c4c7bd8e6e6a6e.svg","alt":"Set-reset conditions","class":"dark:hidden","key":"ZoqUgvf1RE","urlSource":"../../docs/_build/timing/b4a792925037cd4f.svg"},{"type":"image","url":"/PandABlocks-FPGA/docs/build/b4a792925037cd4f.dar-3c0cf2da3fe67f28c064e4dc4617ecc5.svg","alt":"Set-reset conditions","class":"hidden dark:block","key":"PVEc3Tv8bl","urlSource":"../../docs/_build/timing/b4a792925037cd4f.dark.svg"}],"key":"yVoK7LvSaU"}],"key":"HNLYmm5T60"},"references":{"cite":{"order":[],"data":{}}},"footer":{"navigation":{"prev":{"title":"SFP_UDPONTRIG - SFP UDP on trig Module","url":"/sfp-udpontrig-doc","group":"PandABlocks-FPGA"},"next":{"title":"ST_DIO - Separately Terminated Digital Input/Output","url":"/st-dio-doc","group":"PandABlocks-FPGA"}}},"domain":"http://localhost:3000"}